{"data":[{"created_at":"2022-03-03T08:16:09.000Z","in_reply_to_user_id":"1026975826032521216","conversation_id":"1497503501508759555","text":"@Bandanaman4 @derry_down_down thanks Tom. The govt is planning to lock everyone down to do universal testing. Quite a useless move now imho.","author_id":"1088296980","id":"1499297563052175360"},{"created_at":"2022-02-26T20:03:13.000Z","in_reply_to_user_id":"1088296980","conversation_id":"1497503501508759555","text":"@justin_travelog @derry_down_down Stay save. The good thing is that when Omicron case numbers went up so fast they will go down quick once the peak is reached.","author_id":"912372433721716737","id":"1497663565804843009"},{"created_at":"2022-02-26T18:46:57.000Z","in_reply_to_user_id":"1859254296","conversation_id":"1497503501508759555","text":"@TimS_TheToolMan @justin_travelog Eat zinc.","author_id":"833372674462191617","id":"1497644368978718721"},{"created_at":"2022-02-26T17:01:54.000Z","in_reply_to_user_id":"1088296980","conversation_id":"1497503501508759555","text":"@justin_travelog @derry_down_down Justin, I have seen the numbers of new Covid-19 cases in Hong Kong. Hoping that you are well and staying safe. Take care.","author_id":"1026975826032521216","id":"1497617935849959428"},{"created_at":"2022-02-26T16:55:24.000Z","in_reply_to_user_id":"1088296980","conversation_id":"1497503501508759555","text":"@justin_travelog Mask, mask, mask, mask, wash hands, DON'T touch face.......\uD83D\uDE37\uD83D\uDE2C  Stay safe, good luck.","author_id":"1859254296","id":"1497616296502087680"},{"created_at":"2022-02-26T13:27:23.000Z","in_reply_to_user_id":"888749822336958464","conversation_id":"1497503501508759555","text":"@derry_down_down Thanks Jay","author_id":"1088296980","id":"1497563947720839171"},{"created_at":"2022-02-26T13:21:37.000Z","in_reply_to_user_id":"1088296980","conversation_id":"1497503501508759555","text":"@justin_travelog I'm glad to hear that! Stay safe!\uD83D\uDE37","author_id":"888749822336958464","id":"1497562496479203333"},{"created_at":"2022-02-26T13:11:23.000Z","in_reply_to_user_id":"888749822336958464","conversation_id":"1497503501508759555","text":"@derry_down_down Oh no I’m not sick… yet…. But cases have exploded from below 50 to over 10000+ in a matter of a few weeks. So we’re just getting prepped for it","author_id":"1088296980","id":"1497559921151201282"},{"created_at":"2022-02-26T13:07:53.000Z","in_reply_to_user_id":"1088296980","conversation_id":"1497503501508759555","text":"@justin_travelog Are you sick? Or is this your defense team? https://t.co/ahvTL9Zdms","author_id":"888749822336958464","id":"1497559041312178182"},{"created_at":"2022-02-26T12:15:57.000Z","in_reply_to_user_id":"1088296980","conversation_id":"1497503501508759555","text":"@justin_travelog Oh no… get well soon!","author_id":"1362361321338060800","id":"1497545973798744069"}],"meta":{"newest_id":"1499297563052175360","oldest_id":"1497545973798744069","result_count":10}}