{"data":[{"created_at":"2022-03-02T14:06:42.000Z","author_id":"1210802947354808321","conversation_id":"1498890337716162561","in_reply_to_user_id":"18950944","text":"@kw1979 @dennisromboy @Deseret @POTUS Of course you’re not. It’s called head in the sand. You’re in denial about what a failure your president has been. I wonder how bad things will get before you decide to pull your head out?","id":"1499023394435911680"},{"created_at":"2022-03-02T06:28:55.000Z","author_id":"21152332","conversation_id":"1498890337716162561","in_reply_to_user_id":"1979340134","text":"@shelby98046016 @dennisromboy @Deseret @POTUS Once in century pandemic = global inflation regardless of who was President.  \uD83E\uDD37\uD83C\uDFFB‍♀️","id":"1498908191035252736"},{"created_at":"2022-03-02T05:35:32.000Z","author_id":"1979340134","conversation_id":"1498890337716162561","in_reply_to_user_id":"177333933","text":"@dennisromboy @Deseret @POTUS the real State of the Union:\n\n- 2 Embassies Lost \n- Highest Inflation in 40 years  \n- Record High Gas Prices \n- Record High Illegal Border Crossings","id":"1498894755182231555"},{"created_at":"2022-03-02T05:32:36.000Z","author_id":"18950944","conversation_id":"1498890337716162561","in_reply_to_user_id":"177333933","text":"@dennisromboy @Deseret @POTUS Not clicking on this.","id":"1498894016938532873"},{"created_at":"2022-03-02T05:32:29.000Z","author_id":"18950944","conversation_id":"1498890337716162561","in_reply_to_user_id":"177333933","text":"@dennisromboy @Deseret @POTUS Oh, wow. In a state that voted for #TraitorTrump twice?  *Shocking.*","id":"1498893987733594113"}],"meta":{"newest_id":"1499023394435911680","oldest_id":"1498893987733594113","result_count":5}}