{"data":[{"in_reply_to_user_id":"1288180873","conversation_id":"1499659661259067400","id":"1500452857685889033","text":"@Bhekisisa_MG @miamalan @ProfAbdoolKarim Now why would the Gates Foundation be giving R62 MILLION to Bhekisisa Centre for Health Journalism? @miamalan can you explain what that was for? https://t.co/G5EtP2Wu9w","author_id":"1051051860386357248","created_at":"2022-03-06T12:46:52.000Z"},{"in_reply_to_user_id":"1288180873","conversation_id":"1499659661259067400","id":"1500452587727998985","text":"@Bhekisisa_MG @miamalan @ProfAbdoolKarim This is graphene oxide's reaction to 5G radio waves. This is in every vax and ends up in your brain. Imagine what will happen when they turn the 5G on to full power at 64Ghz.\n\nJoin @OfficialBarronTrump https://t.co/p6rD1BLE7Q","author_id":"1051051860386357248","created_at":"2022-03-06T12:45:48.000Z"},{"in_reply_to_user_id":"1288180873","conversation_id":"1499659661259067400","id":"1500002347287822336","text":"@Bhekisisa_MG @miamalan @ProfAbdoolKarim https://t.co/bfKH7FOywD","author_id":"1051051860386357248","created_at":"2022-03-05T06:56:42.000Z"}],"meta":{"newest_id":"1500452857685889033","oldest_id":"1500002347287822336","result_count":3}}