{"data":[{"created_at":"2022-03-06T16:29:17.000Z","author_id":"3854596289","text":"@NicolaPierce3 @Ofmooseandmen Another one for the list. Hope you’re over your bout of Covid.","in_reply_to_user_id":"2691035370","id":"1500508827522846724","conversation_id":"1500428337176616962"},{"created_at":"2022-03-06T11:49:18.000Z","author_id":"900115633031061504","text":"@NicolaPierce3 @Ofmooseandmen ..\uD83C\uDF0A\uD83C\uDF3B\uD83E\uDEC2\uD83D\uDC2C","in_reply_to_user_id":"2691035370","id":"1500438366558502916","conversation_id":"1500428337176616962"},{"created_at":"2022-03-06T11:42:38.000Z","author_id":"39034375","text":"@NicolaPierce3 Thank you.","in_reply_to_user_id":"2691035370","id":"1500436689315115011","conversation_id":"1500428337176616962"}],"meta":{"newest_id":"1500508827522846724","oldest_id":"1500436689315115011","result_count":3}}