{"data":[{"created_at":"2022-03-08T23:36:46.000Z","in_reply_to_user_id":"756213588625199105","id":"1501341182806278153","text":"@GSK_CAN @StephenPunwasi Apartment ventilation = bad","conversation_id":"1501214701182758918","author_id":"328688208"},{"created_at":"2022-03-08T21:50:13.000Z","in_reply_to_user_id":"166364712","id":"1501314371481489410","text":"@StephenPunwasi Elevators and poverty don't make for a healthy mix.","conversation_id":"1501214701182758918","author_id":"2376010136"},{"created_at":"2022-03-08T17:50:10.000Z","in_reply_to_user_id":"166364712","id":"1501253959205502980","text":"@StephenPunwasi Damn, I'm grateful to live in a country that can put together this complex data in a digestible format for people like me. \uD83D\uDE02\uD83E\uDD26‍♂️","conversation_id":"1501214701182758918","author_id":"47251245"},{"created_at":"2022-03-08T16:48:58.000Z","in_reply_to_user_id":"166364712","id":"1501238555728879617","text":"@StephenPunwasi It's all about recycled air in those old buildings. Covid is airborne. New building will need HEPA or MERV 13 filtration. Otherwise they are death traps.","conversation_id":"1501214701182758918","author_id":"38952957"},{"created_at":"2022-03-08T15:32:02.000Z","in_reply_to_user_id":"166364712","id":"1501219195417206784","text":"@StephenPunwasi What exactly are we supposed to do with this extremely useful data?","conversation_id":"1501214701182758918","author_id":"756213588625199105"},{"created_at":"2022-03-08T15:31:17.000Z","in_reply_to_user_id":"166364712","id":"1501219008363864072","text":"@StephenPunwasi So no study to for income or private insurance that is more relevant?","conversation_id":"1501214701182758918","author_id":"137321656"},{"created_at":"2022-03-08T15:24:59.000Z","in_reply_to_user_id":"989362728866377729","id":"1501217422908481551","text":"@Flagpole_Canada haha. It's a pretty perplexing little detail, isn't it? \n\nI'm assuming they didn't correct for location. If you're a low income person living in a single-family home in the middle of nowhere in Newfoundland, your odds of getting sick from COVID are pretty slim.","conversation_id":"1501214701182758918","author_id":"166364712"},{"created_at":"2022-03-08T15:22:51.000Z","in_reply_to_user_id":"166364712","id":"1501216884066242561","text":"@StephenPunwasi So Ur just quoting batman movies now &amp; calling it ur opinion?","conversation_id":"1501214701182758918","author_id":"272576124"},{"created_at":"2022-03-08T15:19:02.000Z","in_reply_to_user_id":"166364712","id":"1501215926204739593","text":"@StephenPunwasi Yup Stephen, Always look at the bright side.. but unfortunately as they become vacant the rent also gets higher","conversation_id":"1501214701182758918","author_id":"985829097602416641"},{"created_at":"2022-03-08T15:18:59.000Z","in_reply_to_user_id":"166364712","id":"1501215911931482114","text":"@StephenPunwasi I guess the lower mortality rate for “low income” in a single family detached was due to fortunes kept from the CRA overseas and/or inherited wealth?","conversation_id":"1501214701182758918","author_id":"989362728866377729"}],"meta":{"newest_id":"1501341182806278153","oldest_id":"1501215911931482114","result_count":10}}