{"data":[{"author_id":"360345939","id":"1501619414919114753","conversation_id":"1501530521746161665","in_reply_to_user_id":"994352010068668416","text":"@TeeExTee news media are creaming themselves they have a new AAA eye-focus topic and can move on from covid, which everyone is bored of. WW3 brings in those ratings.","created_at":"2022-03-09T18:02:21.000Z"},{"author_id":"76047591","id":"1501584358343335938","conversation_id":"1501530521746161665","in_reply_to_user_id":"994352010068668416","text":"@TeeExTee I survived the winter of death. Now I have to survive Biden trying to kill my wallet.","created_at":"2022-03-09T15:43:03.000Z"},{"author_id":"549139778","id":"1501544918564569090","conversation_id":"1501530521746161665","in_reply_to_user_id":"994352010068668416","text":"@TeeExTee Someone jingled their keys louder.","created_at":"2022-03-09T13:06:20.000Z"},{"author_id":"4130199797","id":"1501535613526454275","conversation_id":"1501530521746161665","in_reply_to_user_id":"994352010068668416","text":"@TeeExTee Remember when people were screaming at Spotify trying to cancel Joe Rogan for hosting figures that said anything contrary mainstream narrative? And then Ukraine happened and that’s completely gone like the mob got an order to de-aggro","created_at":"2022-03-09T12:29:22.000Z"}],"meta":{"newest_id":"1501619414919114753","oldest_id":"1501535613526454275","result_count":4}}