{"data":[{"text":"@TimesNow @JM_Scindia Aviation minister with no airlines","conversation_id":"1501171899443068928","author_id":"1316781663578251264","created_at":"2022-03-09T02:09:28.000Z","in_reply_to_user_id":"240649814","id":"1501379614207143937"},{"text":"@TimesNow @JM_Scindia In case, of somethying or anything of, creeps to the mind.. pls don't.hesistate.. sorry about my long awOl.. but then our opposite bldgs are very periscopic?!!. Knapp well and keep well.. no stress...PleaZure as always.. https://t.co/YbyZHVaBhH","conversation_id":"1501171899443068928","author_id":"395791785","created_at":"2022-03-08T18:35:20.000Z","in_reply_to_user_id":"240649814","id":"1501265324062113797"},{"text":"@TimesNow @JM_Scindia Hosi uncle.. hoping all's good on health, and thyngs a re tranquil.. I'm kinda asking..noticing, if you've spotted kinda of an underCurrent.. vz lull fBefOre a storm.. specialist in the tryCks to kids denotion..!? https://t.co/YNtEx1DGHm","conversation_id":"1501171899443068928","author_id":"395791785","created_at":"2022-03-08T18:32:40.000Z","in_reply_to_user_id":"240649814","id":"1501264652667265028"},{"text":"@TimesNow @JM_Scindia Now CA ministry does exactly what! When to start operation normally &amp; when to continue abnormally! Lucky people whoever is associated with this department \uD83D\uDE0E","conversation_id":"1501171899443068928","author_id":"1189225411336556544","created_at":"2022-03-08T17:17:14.000Z","in_reply_to_user_id":"240649814","id":"1501245672502091779"},{"text":"@TimesNow @JM_Scindia Aviation minister with no Aircraft to run !!","conversation_id":"1501171899443068928","author_id":"1043308136","created_at":"2022-03-08T12:57:10.000Z","in_reply_to_user_id":"240649814","id":"1501180224566099970"}],"meta":{"newest_id":"1501379614207143937","oldest_id":"1501180224566099970","result_count":5}}