{"data":[{"text":"@Deniseasteele @Kehlee_ @kerrywcampbell Yesterday i spoke with a medical staff member from Park street and they said they put through over 1100 cars yesterday and then once the change in testing was announced all but 30 cars left.","author_id":"784425409534459904","created_at":"2022-03-09T22:06:03.000Z","id":"1501680742992162825","conversation_id":"1501582492838604800","in_reply_to_user_id":"1270525269128986624"},{"text":"@anna_marie_83 @Kehlee_ @kerrywcampbell Not one car in lineup when I drove by at 1pm","author_id":"1270525269128986624","created_at":"2022-03-09T21:57:11.000Z","id":"1501678512226373640","conversation_id":"1501582492838604800","in_reply_to_user_id":"784425409534459904"},{"text":"@Kehlee_ @kerrywcampbell The change in testing requirements is definitely to reduce the known cases. \n\nWe.basically have to just look after ourselves  now.","author_id":"784425409534459904","created_at":"2022-03-09T21:55:37.000Z","id":"1501678116179263493","conversation_id":"1501582492838604800","in_reply_to_user_id":"3097672239"},{"text":"@kerrywcampbell Pretty sure that's the main reason for the reduced testing.","author_id":"3097672239","created_at":"2022-03-09T21:08:29.000Z","id":"1501666257208287235","conversation_id":"1501582492838604800","in_reply_to_user_id":"29222113"},{"text":"@thesoundmill @kerrywcampbell Oxford suffice? Soy-Boi... https://t.co/VaOfYqz7X3","author_id":"1501226981861605383","created_at":"2022-03-09T19:21:18.000Z","id":"1501639279918956553","conversation_id":"1501582492838604800","in_reply_to_user_id":"838006664"},{"text":"@HippoJoe2 @kerrywcampbell YOU define it, bot.","author_id":"838006664","created_at":"2022-03-09T18:35:39.000Z","id":"1501627795050573831","conversation_id":"1501582492838604800","in_reply_to_user_id":"1501226981861605383"},{"text":"@HippoJoe2 @kerrywcampbell \uD83E\uDD23\uD83E\uDD23\uD83E\uDD23\uD83E\uDD23 https://t.co/GGJTh5gqsw","author_id":"838006664","created_at":"2022-03-09T18:35:16.000Z","id":"1501627696555728902","conversation_id":"1501582492838604800","in_reply_to_user_id":"1501226981861605383"},{"text":"@thesoundmill @kerrywcampbell Define endemic...","author_id":"1501226981861605383","created_at":"2022-03-09T18:27:40.000Z","id":"1501625782568955905","conversation_id":"1501582492838604800","in_reply_to_user_id":"838006664"},{"text":"@thesoundmill @kerrywcampbell Wrong! You’re a #sciencedenier","author_id":"1501226981861605383","created_at":"2022-03-09T18:25:23.000Z","id":"1501625211510263812","conversation_id":"1501582492838604800","in_reply_to_user_id":"838006664"},{"text":"@HippoJoe2 @kerrywcampbell Sorry, which virus is it that you're talking about that's endemic? This thread and conversation is about Covid-19, which, based on these statistics, is clearly not endemic.","author_id":"838006664","created_at":"2022-03-09T17:32:32.000Z","id":"1501611911460401160","conversation_id":"1501582492838604800","in_reply_to_user_id":"1501226981861605383"}],"meta":{"newest_id":"1501680742992162825","oldest_id":"1501611911460401160","result_count":10,"next_token":"b26v89c19zqg8o3fpyqlo4n6pxwubvqce0ldy5efpuiyl"}}