{"data":[{"in_reply_to_user_id":"100774500","created_at":"2022-02-27T07:55:38.000Z","id":"1497842847646691335","conversation_id":"1497682798693519364","text":"@yalchii Yeah the newest I think but already out quite some time","author_id":"2381484243"},{"in_reply_to_user_id":"2381484243","created_at":"2022-02-26T22:09:59.000Z","id":"1497695465059536905","conversation_id":"1497682798693519364","text":"@jAlexCSGO Gute Besserung","author_id":"743562227454705664"},{"in_reply_to_user_id":"2381484243","created_at":"2022-02-26T22:07:07.000Z","id":"1497694745132515328","conversation_id":"1497682798693519364","text":"@jAlexCSGO What's that case?? New ??","author_id":"100774500"},{"in_reply_to_user_id":"3099959215","created_at":"2022-02-26T21:39:23.000Z","id":"1497687766980833285","conversation_id":"1497682798693519364","text":"@17SamMonster \uD83D\uDC9B","author_id":"2381484243"},{"in_reply_to_user_id":"2381484243","created_at":"2022-02-26T21:38:53.000Z","id":"1497687638769569794","conversation_id":"1497682798693519364","text":"@jAlexCSGO Get well soon","author_id":"3099959215"},{"in_reply_to_user_id":"2381484243","created_at":"2022-02-26T21:23:56.000Z","id":"1497683875463630852","conversation_id":"1497682798693519364","text":"Donating one meal per dinner I eat #329\uD83D\uDC9B\n\nJoin me @ShareTheMealorg \uD83D\uDE4F\uD83C\uDFFC https://t.co/bYumQABqah","author_id":"2381484243"}],"meta":{"newest_id":"1497842847646691335","oldest_id":"1497683875463630852","result_count":6}}