{"data":[{"text":"@cliffskarstedt These people need to read the room….there is an actual war taking place in Europe. An unprovoked attack by a real dictator taking away REAL freedoms. In fact I saw a Ukrainian man crossing a destroyed bridge wearing a mask….these “freedom fighters” are ridiculous! Move on.","author_id":"1849542978","created_at":"2022-02-26T18:23:37.000Z","id":"1497638500484661259","conversation_id":"1497617271652601864","in_reply_to_user_id":"110918293"},{"text":"@reynolds_mary @cliffskarstedt Easier for the police to smile and wave at these morons than have to deal with a larger group of citizens who are sick and tired of this moronic behaviour.","author_id":"1327277119","created_at":"2022-02-26T17:57:16.000Z","id":"1497631868329545735","conversation_id":"1497617271652601864","in_reply_to_user_id":"384580227"},{"text":"@cliffskarstedt Police specifically asked counter-protester groups not to attend. Guarantee there’s a lot more of them than this vocal, lawless minority. This is not a reflection of who we are in Peterborough with well over 85% of the community vaccinated &amp; adhering to public health measures.","author_id":"384580227","created_at":"2022-02-26T17:47:57.000Z","id":"1497629523956936709","conversation_id":"1497617271652601864","in_reply_to_user_id":"110918293"}],"meta":{"newest_id":"1497638500484661259","oldest_id":"1497629523956936709","result_count":3}}