{"data":[{"text":"@IndiaWantsMB @MamataOfficial @aitcsudip @JAYADUTTATMC @derekobrienmp @ABHIJIT_LS @Aagan86 @AITCofficial @NirmalGhoshMla @Rathinghoshtmc @SushmitaDevAITC #IndiaWantsMamataDi","author_id":"1096459615984730112","created_at":"2022-03-02T06:34:06.000Z","id":"1498909492750483457","conversation_id":"1498280963905712129","in_reply_to_user_id":"1399729060318650368"},{"text":"@IndiaWantsMB @MamataOfficial @aitcsudip @JAYADUTTATMC @derekobrienmp @ABHIJIT_LS @Aagan86 @AITCofficial @NirmalGhoshMla @Rathinghoshtmc @SushmitaDevAITC According to the report of the Central Government, 7000 crore rupees have been  invested in Bengal , even during covid period .\n\n#IndiaWantsMamataDi","author_id":"1487426182295408640","created_at":"2022-03-01T14:42:07.000Z","id":"1498669917905764366","conversation_id":"1498280963905712129","in_reply_to_user_id":"1399729060318650368"},{"text":"@IndiaWantsMB @MamataOfficial @aitcsudip @JAYADUTTATMC @derekobrienmp @ABHIJIT_LS @Aagan86 @AITCofficial @NirmalGhoshMla @Rathinghoshtmc @SushmitaDevAITC #BreakingNews মোদি সরকারের স্বীকৃতি বাংলাকে, করোনার মধ্যেই মমতার বাংলায় বিনিয়োগ ৭০০০ কোটি টাকা #WestBengal #MamataBanerjee #EgiyeBangla #BengalMeansBusiness #investmentinbengal #bgbs #TMC #AbhishekBanerjee #Modi \nhttps://t.co/3lMtgaIJWX","author_id":"1382856950916947970","created_at":"2022-03-01T10:04:19.000Z","id":"1498600007574122496","conversation_id":"1498280963905712129","in_reply_to_user_id":"1399729060318650368"},{"text":"@IndiaWantsMB @MamataOfficial @aitcsudip @JAYADUTTATMC @derekobrienmp @ABHIJIT_LS @Aagan86 @AITCofficial @NirmalGhoshMla @Rathinghoshtmc @SushmitaDevAITC #IndiaWantsMamataDi\n#IndiaWantsMamataDi\n#IndiaWantsMamataDi\n#IndiaWantsMamataDi\n#IndiaWantsMamataDi\n#IndiaWantsMamataDi\n#IndiaWantsMamataDi\n#IndiaWantsMamataDi\n#IndiaWantsMamataDi\n#IndiaWantsMamataDi\n#IndiaWantsMamataDi\n#IndiaWantsMamataDi\n#IndiaWantsMamataDi\n#IndiaWantsMamataDi","author_id":"1426384524934402056","created_at":"2022-03-01T05:51:48.000Z","id":"1498536461829689345","conversation_id":"1498280963905712129","in_reply_to_user_id":"1399729060318650368"},{"text":"@IndiaWantsMB @MamataOfficial @aitcsudip @JAYADUTTATMC @derekobrienmp @ABHIJIT_LS @Aagan86 @AITCofficial @NirmalGhoshMla @Rathinghoshtmc তামিলনাড়ুতে কি ওই সময়তে Rs. 67000/- crores? May be wrong, still if scenarios were like these then we need to take more positive steps to attract more investment in WB.","author_id":"1474728204141137920","created_at":"2022-03-01T05:00:25.000Z","id":"1498523528345255938","conversation_id":"1498280963905712129","in_reply_to_user_id":"1399729060318650368"},{"text":"@IndiaWantsMB @MamataOfficial @aitcsudip @JAYADUTTATMC @derekobrienmp @ABHIJIT_LS @Aagan86 @AITCofficial @NirmalGhoshMla @Rathinghoshtmc @SushmitaDevAITC ১৯৮৬ ব্যাচের এই আইপিএস অফিসার মদন মোহন মালব্য অখিল ভারতীয় হিন্দু মহাসভার প্রতিষ্ঠাতা।ডিজির বাবার নাম গিরিধর মালব্য,উনি ২০১৪ সালে লোকসভা ভোটে নরেন্দ্র মোদীর মনোনয়নপত্রে চারজন প্রস্তাবকের অন্যতম...\nকেন ওনাকেই মমতা ব্যানার্জি ডিজির পদে বেছেছিলেন সেই ব্যাখ্যা না বুঝলে \uD83D\uDC61জুতো চাটুন","author_id":"1432068513733152771","created_at":"2022-03-01T04:21:08.000Z","id":"1498513644744806402","conversation_id":"1498280963905712129","in_reply_to_user_id":"1399729060318650368"},{"text":"@IndiaWantsMB @MamataOfficial @aitcsudip @JAYADUTTATMC @derekobrienmp @ABHIJIT_LS @Aagan86 @AITCofficial @NirmalGhoshMla @Rathinghoshtmc @SushmitaDevAITC Didi, I am proud of you \uD83D\uDC9A✌️\uD83D\uDE4F","author_id":"1405725884728807426","created_at":"2022-03-01T04:16:08.000Z","id":"1498512386994556935","conversation_id":"1498280963905712129","in_reply_to_user_id":"1399729060318650368"},{"text":"@IndiaWantsMB @MamataOfficial @aitcsudip @JAYADUTTATMC @derekobrienmp @ABHIJIT_LS @Aagan86 @AITCofficial @NirmalGhoshMla @Rathinghoshtmc @SushmitaDevAITC #IndiaWantsMamataDi","author_id":"1297934164172271616","created_at":"2022-03-01T03:44:47.000Z","id":"1498504496510500867","conversation_id":"1498280963905712129","in_reply_to_user_id":"1399729060318650368"},{"text":"@IndiaWantsMB @MamataOfficial @aitcsudip @JAYADUTTATMC @derekobrienmp @ABHIJIT_LS @Aagan86 @AITCofficial @NirmalGhoshMla @Rathinghoshtmc @SushmitaDevAITC #IndiaWantsMamataDi","author_id":"1472250710259638272","created_at":"2022-03-01T02:09:48.000Z","id":"1498480592253435909","conversation_id":"1498280963905712129","in_reply_to_user_id":"1399729060318650368"},{"text":"@IndiaWantsMB @MamataOfficial @aitcsudip @JAYADUTTATMC @derekobrienmp @ABHIJIT_LS @Aagan86 @AITCofficial @NirmalGhoshMla @Rathinghoshtmc @SushmitaDevAITC #উন্নয়ন মানে @MamataOfficial\n#বাংলার আবেগ @MamataOfficial \n#বৈপ্লবিক আন্দোলন মানে @MamataOfficial\n#বঞ্চনা ও প্রতিবাদ মানে @MamataOfficial\n#শিল্পের জন্য লড়াই মানে @MamataOfficial","author_id":"1381878106282024961","created_at":"2022-03-01T00:39:39.000Z","id":"1498457905611546625","conversation_id":"1498280963905712129","in_reply_to_user_id":"1399729060318650368"}],"meta":{"newest_id":"1498909492750483457","oldest_id":"1498457905611546625","result_count":10,"next_token":"b26v89c19zqg8o3fpe789bh31q9mrvsjxitb9z7w1429p"}}