{"data":[{"created_at":"2022-03-10T23:46:11.000Z","in_reply_to_user_id":"14237983","author_id":"14237983","conversation_id":"1499872740710522880","text":"@JamesDeVille https://t.co/EOUPjPrgwW","id":"1502068330412265483"},{"created_at":"2022-03-10T23:45:30.000Z","in_reply_to_user_id":"106127110","author_id":"14237983","conversation_id":"1499872740710522880","text":"@JamesDeVille https://t.co/CwVYYuZi0i","id":"1502068156860448768"},{"created_at":"2022-03-09T02:27:11.000Z","in_reply_to_user_id":"106127110","author_id":"2365956168","conversation_id":"1499872740710522880","text":"@JamesDeVille Thanks for the motion and the yes vote tonight!","id":"1501384070294642695"},{"created_at":"2022-03-08T18:39:28.000Z","in_reply_to_user_id":"106127110","author_id":"463793966","conversation_id":"1499872740710522880","text":"@JamesDeVille Masking is causing anxiety in children who are not in danger of sickness and even if they do get sick, they recover quickly. Optional is the only right thing to do. Schools are the only reminder of this damn virus. The rest of the world has moved on. What message are we sending.","id":"1501266364891336708"},{"created_at":"2022-03-08T05:34:13.000Z","in_reply_to_user_id":"106127110","author_id":"8746882","conversation_id":"1499872740710522880","text":"@JamesDeVille As a constituent and a public health expert, I strongly urge you not to go mask optional. Do you want to stay in yellow? Or go to red? I still think with #BA2 coming up behind us green is far away.","id":"1501068751432822786"},{"created_at":"2022-03-07T00:55:15.000Z","in_reply_to_user_id":"765732874272251904","author_id":"1360957674263883777","conversation_id":"1499872740710522880","text":"@geminisallday @JamesDeVille https://t.co/9QZ2etAkDS","id":"1500636157402624001"},{"created_at":"2022-03-05T20:42:38.000Z","in_reply_to_user_id":"106127110","author_id":"78663175","conversation_id":"1499872740710522880","text":"@JamesDeVille I appreciate your efforts but I have ZER0 faith in the rest of the JCPS board. Most do the opposite of what parents, kids and teachers want out of spite. They have made that clear.","id":"1500210197008105479"},{"created_at":"2022-03-05T20:35:58.000Z","in_reply_to_user_id":"106127110","author_id":"695664497260756992","conversation_id":"1499872740710522880","text":"@JamesDeVille Unmask my kid, seriously nobody is requiring them except @JCPSSuper @JCPSKY","id":"1500208519869571086"},{"created_at":"2022-03-05T14:37:05.000Z","in_reply_to_user_id":"106127110","author_id":"486074045","conversation_id":"1499872740710522880","text":"@JamesDeVille We need to reduce from 10 to 5 days first!!","id":"1500118205762879489"},{"created_at":"2022-03-05T14:30:32.000Z","in_reply_to_user_id":"1360957674263883777","author_id":"273737006","conversation_id":"1499872740710522880","text":"@Unmask_the_kids @JamieLeaLou @JamesDeVille \"Might even\"","id":"1500116555442630656"}],"meta":{"newest_id":"1502068330412265483","oldest_id":"1500116555442630656","result_count":10,"next_token":"b26v89c19zqg8o3fpyql8odm9sdcpwd5w1dsgqy15xfnh"}}