{"data":[{"text":"@WHOAFRO \uD83D\uDC4D\uD83E\uDD18\uD83E\uDDBE\uD83E\uDD70\uD83D\uDE0D❤️\uD83D\uDE4F\uD83D\uDE07","conversation_id":"1500763999285170178","created_at":"2022-03-08T05:55:20.000Z","author_id":"1415951737249157120","id":"1501074066945441795","in_reply_to_user_id":"544389588"},{"text":"@WHOAFRO SveErthNtrePplWldlfebyonewndw\noprtnPlnttrilionsNeemtrees@evry\nnck&amp;crnrofWrldPrvdeU24hrsoxygn\n(Onlytre)&amp;sckalcrbnfrmatmsphr\nUachveZrocrbnCntrlClmtchnge\nNrmlzetmprtrRdceGlblwrmng\nSprvccnRmvealinfctsdisswth100%\nrcvryVrsklrBldprtrHghptntlfrtlzr&amp;\nStrngdzpstcdsIncrsealcrpyld\nCmeprprpth","conversation_id":"1500763999285170178","created_at":"2022-03-07T14:25:33.000Z","author_id":"959344946322051072","id":"1500840077244653576","in_reply_to_user_id":"544389588"},{"text":"@WHOAFRO NowyOnlyoneprfctDntwstetmeDnt\naplytmprymnylstwysNwarngmntsnt\ngveUefctversltsBesnsblStpdths\nRstreUractvtsAdpt100%rcvrytrtmnt\nRmvCorona/Cncrs/HIV/anyinfcts\ndissbyNeemTonic2Dzdly(mdeNmtre\nlvs)SprvccnPrtctalnrvPrvdealtme\noxygnClnalsystmsUseVrslsetrnsfr\npwrNosdefctVrsklrBldprtrFlfeSvr","conversation_id":"1500763999285170178","created_at":"2022-03-07T14:21:24.000Z","author_id":"959344946322051072","id":"1500839035392122880","in_reply_to_user_id":"544389588"},{"text":"@WHOAFRO Governments are forcibly vaccinating people and pushing them to the brink of death.  Save yourself and your loved ones from the valley of death (vaccine). The WHO has made it clear that.  The vaccine does not work alone against covid-19. vaccine is a silent and cunning killer .","conversation_id":"1500763999285170178","created_at":"2022-03-07T11:21:50.000Z","author_id":"1383982952875380748","id":"1500793842672484354","in_reply_to_user_id":"544389588"},{"text":"@WHOAFRO https://t.co/0PXmzENelE","conversation_id":"1500763999285170178","created_at":"2022-03-07T09:29:08.000Z","author_id":"1469807450282942475","id":"1500765482055606276","in_reply_to_user_id":"544389588"},{"text":"@WHOAFRO BS https://t.co/SInAvTANeH","conversation_id":"1500763999285170178","created_at":"2022-03-07T09:27:03.000Z","author_id":"216059100","id":"1500764959474692097","in_reply_to_user_id":"544389588"},{"text":"@WHOAFRO Minimize close contact that spreads new variant, use app Bost instead to communicate safely with people within the same street block or even the same building. Download for free at Apple https://t.co/uChWynVbJG &amp; Google https://t.co/Nvi0yitq3f https://t.co/FvJfnOPDyF","conversation_id":"1500763999285170178","created_at":"2022-03-07T09:23:43.000Z","author_id":"884827243553411072","id":"1500764118860578820","in_reply_to_user_id":"544389588"}],"meta":{"newest_id":"1501074066945441795","oldest_id":"1500764118860578820","result_count":7}}