{"data":[{"conversation_id":"1500309579057569792","text":"@nzherald They should have retained more of the 500 contact tracers that they let go.","author_id":"2683271568","created_at":"2022-03-06T18:58:00.000Z","id":"1500546255042531336","in_reply_to_user_id":"14765253"},{"conversation_id":"1500309579057569792","text":"@nzherald Dr. Robert Malone: \"What We Have Is Negative Efficacy\"\n\n\"Clearly, we have data from all over the world demonstrating that the [shots] and multiple [shots] is actually increasing the risk of people for getting Omicron-mediated disease and potentially even death.\"","author_id":"1291243812988186625","created_at":"2022-03-06T09:53:00.000Z","id":"1500409102656106498","in_reply_to_user_id":"14765253"},{"conversation_id":"1500309579057569792","text":"@nzherald Put it in the scanning app. It’s the only useful thing that does now and it has all your info.","author_id":"1479674401918369792","created_at":"2022-03-06T03:30:40.000Z","id":"1500312883967971332","in_reply_to_user_id":"14765253"},{"conversation_id":"1500309579057569792","text":"@nzherald Cheers fellas.. this dat shit we peeps want ta no.","author_id":"1494219103112146944","created_at":"2022-03-06T03:23:12.000Z","id":"1500311005707968513","in_reply_to_user_id":"14765253"},{"conversation_id":"1500309579057569792","text":"@nzherald https://t.co/n6dENj6Flf","author_id":"1494219103112146944","created_at":"2022-03-06T03:22:26.000Z","id":"1500310810404417546","in_reply_to_user_id":"14765253"}],"meta":{"newest_id":"1500546255042531336","oldest_id":"1500310810404417546","result_count":5}}