{"data":[{"conversation_id":"1501938741237084168","text":"@annemariepoet Agreed!","in_reply_to_user_id":"1377945669546209282","author_id":"989190883873521664","id":"1502055259555999757","created_at":"2022-03-10T22:54:15.000Z"},{"conversation_id":"1501938741237084168","text":"@annemariepoet Yeah, excuse my bot 'splaining.","in_reply_to_user_id":"1377945669546209282","author_id":"1036741476200394753","id":"1502047916453769243","created_at":"2022-03-10T22:25:04.000Z"},{"conversation_id":"1501938741237084168","text":"@annemariepoet Bed, painkillers and some books.","in_reply_to_user_id":"1377945669546209282","author_id":"280209413","id":"1501967924432625668","created_at":"2022-03-10T17:07:13.000Z"},{"conversation_id":"1501938741237084168","text":"@Littlemisskatyb I'm dreading catching it again. \nWe've had it twice. \nHow are you doing today?\nI hope you're looking after yourself.","in_reply_to_user_id":"280209413","author_id":"1377945669546209282","id":"1501965284969746437","created_at":"2022-03-10T16:56:43.000Z"},{"conversation_id":"1501938741237084168","text":"@annemariepoet I know of at least four people currently with it for the second time…","in_reply_to_user_id":"1377945669546209282","author_id":"280209413","id":"1501964078943772678","created_at":"2022-03-10T16:51:56.000Z"},{"conversation_id":"1501938741237084168","text":"@puppy_slash uh \nyes\nI know","in_reply_to_user_id":"1036741476200394753","author_id":"1377945669546209282","id":"1501959178679693316","created_at":"2022-03-10T16:32:27.000Z"},{"conversation_id":"1501938741237084168","text":"@annemariepoet I think part of motive behind this (by the state at least) is precisely the rejection of collectivism in favour of \"I'm alright Jack\" individualism.","in_reply_to_user_id":"1377945669546209282","author_id":"1036741476200394753","id":"1501949845870821388","created_at":"2022-03-10T15:55:22.000Z"},{"conversation_id":"1501938741237084168","text":"@annemariepoet Uhhh wait, what did I say??? I was typing while walking around a thrift shop and I think some wires in my brain got crossed \uD83D\uDE02\uD83D\uDE02\uD83D\uDE02","in_reply_to_user_id":"1199228328256983040","author_id":"1199228328256983040","id":"1501946863729070091","created_at":"2022-03-10T15:43:31.000Z"},{"conversation_id":"1501938741237084168","text":"@annemariepoet Imagine requiring a hazmat suit for public transport, these people would be screaming about personal freedoms with their eyebrows literally popping out their eyeballs like corn kernels \uD83D\uDE02","in_reply_to_user_id":"1377945669546209282","author_id":"1199228328256983040","id":"1501944560372510729","created_at":"2022-03-10T15:34:22.000Z"},{"conversation_id":"1501938741237084168","text":"@Brainworm_Joy People bleeding liquefied organs on public transport. \nI can see it.","in_reply_to_user_id":"1199228328256983040","author_id":"1377945669546209282","id":"1501941838940295173","created_at":"2022-03-10T15:23:33.000Z"}],"meta":{"newest_id":"1502055259555999757","oldest_id":"1501941838940295173","result_count":10,"next_token":"b26v89c19zqg8o3fpyqlob29j7phijnhu7b2tc1hgzdkt"}}