{"data":[{"author_id":"415274173","id":"1502177062232080387","conversation_id":"1501850294543654914","in_reply_to_user_id":"2203396901","text":"@ahmedirfanmka اللّٰہ فضل فرمائے اور ہر قسم کی پیچیدگی سے محفوظ رکھے۔ آمین","created_at":"2022-03-11T06:58:15.000Z"},{"author_id":"1482061698102181894","id":"1502151755307442182","conversation_id":"1501850294543654914","in_reply_to_user_id":"2203396901","text":"@ahmedirfanmka God bless you and everyone","created_at":"2022-03-11T05:17:41.000Z"},{"author_id":"2203396901","id":"1502034051359821825","conversation_id":"1501850294543654914","in_reply_to_user_id":"43108958","text":"@safeery2k @just_nabil \uD83D\uDE1C\uD83D\uDE1C","created_at":"2022-03-10T21:29:58.000Z"},{"author_id":"43108958","id":"1502033571011346439","conversation_id":"1501850294543654914","in_reply_to_user_id":"2203396901","text":"@ahmedirfanmka @just_nabil It was your plan, you were concerned about food more than cricket \uD83D\uDE2C","created_at":"2022-03-10T21:28:04.000Z"},{"author_id":"952110214815232000","id":"1502015456663650330","conversation_id":"1501850294543654914","in_reply_to_user_id":"2203396901","text":"@ahmedirfanmka May Allah Tàla grant you speedy recovery Ameen sum Ameen","created_at":"2022-03-10T20:16:05.000Z"},{"author_id":"785212350156668928","id":"1501924173739921418","conversation_id":"1501850294543654914","in_reply_to_user_id":"2203396901","text":"@ahmedirfanmka May Allah give you and family speedy recovery and complete health soon ameen.","created_at":"2022-03-10T14:13:22.000Z"},{"author_id":"937460936","id":"1501921996992651269","conversation_id":"1501850294543654914","in_reply_to_user_id":"2203396901","text":"@ahmedirfanmka May Allah bless you all, with a swift and complete Shifa, Ameen","created_at":"2022-03-10T14:04:43.000Z"},{"author_id":"3185259614","id":"1501916608863752195","conversation_id":"1501850294543654914","in_reply_to_user_id":"43108958","text":"@safeery2k @ahmedirfanmka Mashallah","created_at":"2022-03-10T13:43:18.000Z"},{"author_id":"2380760752","id":"1501916339681861634","conversation_id":"1501850294543654914","in_reply_to_user_id":"2203396901","text":"@ahmedirfanmka Khana phr ghr ke bahir Rakh dn please. I'll pick it up \uD83D\uDE02. Allah tallah fazal kre r Apne hifz o amaan mein rakhe.","created_at":"2022-03-10T13:42:14.000Z"},{"author_id":"2203396901","id":"1501915717310033925","conversation_id":"1501850294543654914","in_reply_to_user_id":"1154478222","text":"@just_nabil you and safeer both are the culprits","created_at":"2022-03-10T13:39:45.000Z"}],"meta":{"newest_id":"1502177062232080387","oldest_id":"1501915717310033925","result_count":10,"next_token":"b26v89c19zqg8o3fpyqlob1dbzuwra15txwk372qkxunx"}}